All_In_One/__init__.py
All_In_One/__main__.py
All_In_One/all_in_one.py
all_in_one-0.0.1.dist-info/LICENSE
all_in_one-0.0.1.dist-info/METADATA
all_in_one-0.0.1.dist-info/WHEEL
all_in_one-0.0.1.dist-info/top_level.txt
all_in_one-0.0.1.dist-info/RECORD
