Metadata-Version: 2.1
Name: all-in-one
Version: 0.0.1
Summary: This is an all in one package that helps you to do a lot of things like audio, video, networks, web, etc.
Home-page: https://github.com/pypa/sampleproject
Author: Abhishek A
Author-email: abhishek@gmail.com
License: UNKNOWN
Project-URL: Bug Tracker, https://github.com/pypa/sampleproject/issues
Platform: UNKNOWN
Classifier: Programming Language :: Python :: 3
Classifier: License :: OSI Approved :: MIT License
Classifier: Operating System :: OS Independent
Requires-Python: >=3.6
